{
  "data": [
    {
      "id": "MDEwOlJlcG9zaXRvcnkyNDU0NjcyNzQ=",
      "name": "Proffy",
      "createdAt": "2020-08-03T16:26:54Z",
      "url": "https://github.com/Willian17/proffy-nlw2",
      "description": "Professores darem aulas particulares para alunos",
      "isFork": false,
      "languages": [
        {
          "name": "Node.js",
          "iconifyClass": "logos-nodejs"
        },
        {
          "name": "React.js",
          "iconifyClass": "logos-react"
        },
        {
          "name": "TypeScript",
          "iconifyClass": "logos-typescript"
        },
        {
          "name": "React Native",
          "iconifyClass": "logos-react"
        }
      ]
    },
    {
      "id": "MDEwOlJlcG9zaXRvcnkyNDU0NjdghhgyNzQ=",
      "name": "Controle de Filiais",
      "createdAt": "2020-06-03T16:26:54Z",
      "url": "https://github.com/Willian17/softsul-crud",
      "description": "Controlar filiais a partir da empresa matriz",
      "isFork": false,
      "languages": [
        {
          "name": "Node.js",
          "iconifyClass": "logos-nodejs"
        },
        {
          "name": "Vue.js",
          "iconifyClass": "logos-vue"
        },
        {
          "name": "React Native",
          "iconifyClass": "logos-react"
        }
      ]
    },
    {
      "id": "MDEwOlJlcG9fghfghfghhjdghhgyNzQ=",
      "name": "Weight history",
      "createdAt": "2020-07-20T16:26:54Z",
      "url": "https://github.com/Willian17/weight-history",
      "description": "Guardar Histórico de pesos de uma pessoa",
      "isFork": false,
      "languages": [
        {
          "name": "Node.js",
          "iconifyClass": "logos-nodejs"
        },
        {
          "name": "React.js",
          "iconifyClass": "logos-react"
        },
        {
          "name": "React Native",
          "iconifyClass": "logos-react"
        }
      ]
    },
    {
      "id": "MDEwOlJlcG9zaXdfdfgdfgdfgfdggyNzQ=",
      "name": "BrainIF",
      "createdAt": "2020-05-02T16:26:54Z",
      "url": "https://github.com/Willian17/brainif-complete",
      "description": "Fórum para alunos tirarem suas dúvidas com professores",
      "isFork": false,
      "languages": [
        {
          "name": "Node.js",
          "iconifyClass": "logos-nodejs"
        },
        {
          "name": "Vue.js",
          "iconifyClass": "logos-vue"
        }
      ]
    },
    {
      "id": "MDEwOlJlcG9zaXRvcnkydfgdfghdfhjdghhgyNzQ=",
      "name": "WilFlix",
      "createdAt": "2020-07-25T16:26:54Z",
      "url": "https://github.com/Willian17/WilFlix",
      "description": "Netflix com seus próprios conteúdos, videos, filmes e séries",
      "isFork": false,
      "languages": [
        {
          "name": "React.js",
          "iconifyClass": "logos-react"
        }
      ]
    },
    {
      "id": "MDEwOlJlcG9zfghfghfhhdfhjdghhgyNzQ=",
      "name": "Jogo Multiplayer",
      "createdAt": "2020-07-06T16:26:54Z",
      "url": "https://github.com/Willian17/meu-primeiro-jogo-multiplayer",
      "description": "Um jogo multiplayer usando conceitos de arquitetura de software",
      "isFork": false,
      "languages": [
        {
          "name": "Node.js",
          "iconifyClass": "logos-nodejs"
        },
        {
          "name": "Html",
          "iconifyClass": "logos-html-5"
        },
        {
          "name": "Css",
          "iconifyClass": "logos-css-3"
        }
      ]
    }
  ]
}
